Metadata-Version: 2.1
Name: speeshare
Version: 0.0.2
Summary: A small FILEtoURL package.
Author-email: Fander Company <help@fandercompany.ru>
Project-URL: Homepage, https://github.com/Fander-Company/speeshare
Project-URL: Bug Tracker, https://github.com/Fander-Company/speeshare/issues
Classifier: Programming Language :: Python :: 3
Classifier: License :: OSI Approved :: MIT License
Classifier: Operating System :: OS Independent
Requires-Python: >=3.7
License-File: LICENSE
